LICENSE
README.md
pyproject.toml
setup.py
okmathutils/__init__.py
okmathutils.egg-info/PKG-INFO
okmathutils.egg-info/SOURCES.txt
okmathutils.egg-info/dependency_links.txt
okmathutils.egg-info/top_level.txt