Metadata-Version: 2.1
Name: okmathutils
Version: 0.0.5
Summary: Simple math utilities for python
Home-page: https://github.com/HoomanBud/OpenMathUtils
Author: Hooman Bud
Author-email: hoomanbud5511@gmail.com
License: MIT
Platform: UNKNOWN
License-File: LICENSE
